emlinefit/__init__.py
emlinefit/emlinefit.py
emlinefit-1.0.0.dist-info/licenses/LICENSE.txt
emlinefit-1.0.0.dist-info/METADATA
emlinefit-1.0.0.dist-info/WHEEL
emlinefit-1.0.0.dist-info/top_level.txt
emlinefit-1.0.0.dist-info/RECORD
