Metadata-Version: 2.4
Name: emlinefit
Version: 1.0.0
License-File: LICENSE.txt
Requires-Dist: numpy
Requires-Dist: pandas
Requires-Dist: matplotlib
Requires-Dist: scipy
Dynamic: license-file
